decimate/__init__.py
decimate/decimate.py
decimate/engine.py
decimate/env.py
decimate/run_test.py
decimate/slurm_frontend.py
decimate-0.9.6.data/data/AUTHORS
decimate-0.9.6.data/data/LICENSE.txt
decimate-0.9.6.data/data/share/man/man1/decimate.1
decimate-0.9.6.data/data/share/man/man1/workflow.1
decimate-0.9.6.data/data/tests/error_pb_job.sh
decimate-0.9.6.data/data/tests/error_pb_params.sh
decimate-0.9.6.data/data/tests/tests.sh
decimate-0.9.6.dist-info/DESCRIPTION.rst
decimate-0.9.6.dist-info/METADATA
decimate-0.9.6.dist-info/RECORD
decimate-0.9.6.dist-info/WHEEL
decimate-0.9.6.dist-info/entry_points.txt
decimate-0.9.6.dist-info/metadata.json
decimate-0.9.6.dist-info/top_level.txt
