Metadata-Version: 2.0
Name: decimate
Version: 0.9.6
Summary: A fault-tolerant SLURM scheduler extension
Home-page: http://decimate.readthedocs.io
Author: Samuel KORTAS
Author-email: samuel.kortas@kaust.edu.sa
Maintainer: Samuel KORTAS
Maintainer-email: samuel.kortas@kaust.edu.sa
License: UNKNOWN
Keywords: scheduler extension workflow parametric
Platform: UNKNOWN
Classifier: Development Status :: 3 - Alpha
Classifier: Environment :: Console
Classifier: Intended Audience :: Science/Research
Classifier: Topic :: Software Development :: Build Tools
Classifier: License :: OSI Approved :: BSD License
Classifier: Programming Language :: Python :: 2
Classifier: Programming Language :: Python :: 2.7
Classifier: Operating System :: POSIX
Classifier: Topic :: Software Development :: Libraries :: Python Modules
Classifier: Topic :: System :: Clustering
Classifier: Topic :: System :: Distributed Computing
Classifier: Topic :: Utilities
Requires-Python: >=2.7,  <3
Provides-Extra: test
Provides-Extra: dev
Requires-Dist: ClusterShell
Requires-Dist: pandas
Provides-Extra: dev
Requires-Dist: check-manifest; extra == 'dev'
Provides-Extra: test
Requires-Dist: coverage; extra == 'test'
